corpus_preprocess/__init__.py
corpus_preprocess/abstracts.py
corpus_preprocess/artifacts.py
corpus_preprocess/concepts.py
corpus_preprocess/main.py
corpus_preprocess/preprocessor/__init__.py
corpus_preprocess/preprocessor/build_abbreviations.py
corpus_preprocess/preprocessor/build_digits.py
corpus_preprocess/preprocessor/build_serials.py
corpus_preprocess/preprocessor/patterns_date.py
corpus_preprocess/preprocessor/patterns_docket.py
corpus_preprocess/preprocessor/patterns_juridical.py
corpus_preprocess/preprocessor/patterns_report.py
corpus_preprocess/preprocessor/patterns_statute.py
corpus_preprocess/preprocessor/patterns_unit.py
corpus_preprocess/preprocessor/patterns_vs.py
corpus_preprocess/preprocessor/utils.py
corpus_preprocess/tokenizer.py
corpus_preprocess-0.0.7.dist-info/METADATA
corpus_preprocess-0.0.7.dist-info/WHEEL
corpus_preprocess-0.0.7.dist-info/RECORD
