Metadata-Version: 2.1
Name: corpus-preprocess
Version: 0.0.7
Summary: Utility functions to preprocess Phil. legalese in weasel-based flows.
Home-page: https://mv3.dev
Author: Marcelino G. Veloso III
Author-email: contact@mv3.dev
Requires-Python: >=3.11,<4.0
Classifier: Programming Language :: Python :: 3
Classifier: Programming Language :: Python :: 3.11
Classifier: Programming Language :: Python :: 3.12
Requires-Dist: inflect (>=7.0,<8.0)
Requires-Dist: ipykernel (>=6.27.1,<7.0.0)
Requires-Dist: rich (>=13.7.0,<14.0.0)
Requires-Dist: roman (>=4.1,<5.0)
Requires-Dist: spacy[apple] (>=3.7.2,<4.0.0)
Project-URL: Documentation, https://justmars.github.io/corpus-preprocess
Project-URL: Repository, https://github.com/justmars/corpus-preprocess
